eatpy/__init__.py
eatpy/default_files/__init__.py
eatpy/default_files/_dockerignore.py
eatpy/default_files/_gitignore.py
eatpy/default_files/settings_json.py
eatpy/default_files/aws_lambda/__init__.py
eatpy/default_files/aws_lambda/app_py.py
eatpy/default_files/aws_lambda/build_and_test_sh.py
eatpy/default_files/aws_lambda/buildfile.py
eatpy/default_files/aws_lambda/buildfile_conda.py
eatpy/default_files/aws_lambda/environment_yml.py
eatpy/default_files/aws_lambda/task_py.py
eatpy/default_files/package/__init__.py
eatpy/default_files/package/pyproject_toml.py
eatpy/default_files/package/setup_cfg.py
eatpy/scripts/__init__.py
eatpy/scripts/scripts.py
eatpy/templates/__init__.py
eatpy/templates/aws_lambda.py
eatpy/templates/common.py
eatpy/templates/package.py
eatpy/templates/settings.py
eatpy-2022.10.1.dist-info/LICENSE
eatpy-2022.10.1.dist-info/METADATA
eatpy-2022.10.1.dist-info/WHEEL
eatpy-2022.10.1.dist-info/entry_points.txt
eatpy-2022.10.1.dist-info/top_level.txt
eatpy-2022.10.1.dist-info/RECORD
